[{"Arrest":"false","Beat":"1722","Block":"043XX W MONTROSE AVE","Case Number":"JH497594","Community Area":"16","Date":"11/01/2024 12:00:00 AM","Description":"THEFT FROM MOTOR VEHICLE","District":"017","Domestic":"false","FBI Code":"06","ID":"13654954","IUCR":"0710","Latitude":"41.960858577","Location":"(41.960858577, -87.735994826)","Location Description":"PARKING LOT / GARAGE (NON RESIDENTIAL)","Longitude":"-87.735994826","Primary Type":"THEFT","Updated On":"11/08/2024 03:41:24 PM","Ward":"39","X Coordinate":"1146714","Y Coordinate":"1928893","Year":"2024"},{"Arrest":"true","Beat":"0811","Block":"056XX S MONITOR AVE","Case Number":"JH490976","Community Area":"56","Date":"10/31/2024 11:25:00 PM","Description":"OTHER VEHICLE OFFENSE","District":"008","Domestic":"true","FBI Code":"26","ID":"13649601","IUCR":"5002","Latitude":"41.789967349","Location":"(41.789967349, -87.7683057)","Location Description":"DRIVEWAY - RESIDENTIAL","Longitude":"-87.7683057","Primary Type":"OTHER OFFENSE","Updated On":"11/08/2024 03:41:24 PM","Ward":"13","X Coordinate":"1138336","Y Coordinate":"1866561","Year":"2024"},{"Arrest":"false","Beat":"1135","Block":"028XX W POLK ST","Case Number":"JH490983","Community Area":"27","Date":"10/31/2024 11:53:00 PM","Description":"$500 AND UNDER","District":"011","Domestic":"false","FBI Code":"06","ID":"13649623","IUCR":"0820","Latitude":"41.871055371","Location":"(41.871055371, -87.696987711)","Location Description":"ALLEY","Longitude":"-87.696987711","Primary Type":"THEFT","Updated On":"11/08/2024 03:41:24 PM","Ward":"28","X Coordinate":"1157566","Y Coordinate":"1896245","Year":"2024"},{"Arrest":"true","Beat":"0621","Block":"080XX S EMERALD AVE","Case Number":"JH490985","Community Area":"71","Date":"10/31/2024 11:21:00 PM","Description":"UNLAWFUL POSSESSION - HANDGUN","District":"006","Domestic":"false","FBI Code":"15","ID":"13649563","IUCR":"143A","Latitude":"41.747974023","Location":"(41.747974023, -87.642745358)","Location Description":"STREET","Longitude":"-87.642745358","Primary Type":"WEAPONS VIOLATION","Updated On":"11/08/2024 03:41:24 PM","Ward":"6","X Coordinate":"1172700","Y Coordinate":"1851509","Year":"2024"},{"Arrest":"false","Beat":"0313","Block":"061XX S ST LAWRENCE AVE","Case Number":"JH491001","Community Area":"42","Date":"11/01/2024 12:00:00 AM","Description":"ARMED - HANDGUN","District":"003","Domestic":"false","FBI Code":"03","ID":"13649555","IUCR":"031A","Latitude":"41.783514269","Location":"(41.783514269, -87.610875615)","Location Description":"STREET","Longitude":"-87.610875615","Primary Type":"ROBBERY","Updated On":"11/08/2024 03:41:24 PM","Ward":"20","X Coordinate":"1181288","Y Coordinate":"1864531","Year":"2024"},{"Arrest":"false","Beat":"1934","Block":"007XX W BELMONT AVE","Case Number":"JH491018","Community Area":"6","Date":"10/31/2024 11:50:00 PM","Description":"TO PROPERTY","District":"019","Domestic":"false","FBI Code":"14","ID":"13649585","IUCR":"1310","Latitude":"41.940005868","Location":"(41.940005868, -87.647690125)","Location Description":"HOTEL / MOTEL","Longitude":"-87.647690125","Primary Type":"CRIMINAL DAMAGE","Updated On":"11/08/2024 03:41:24 PM","Ward":"44","X Coordinate":"1170792","Y Coordinate":"1921474","Year":"2024"},{"Arrest":"true","Beat":"1034","Block":"027XX W 26TH ST","Case Number":"JH490965","Community Area":"30","Date":"10/31/2024 11:18:00 PM","Description":"DOMESTIC BATTERY SIMPLE","District":"010","Domestic":"true","FBI Code":"08B","ID":"13649533","IUCR":"0486","Latitude":"41.844715359","Location":"(41.844715359, -87.693417234)","Location Description":"APARTMENT","Longitude":"-87.693417234","Primary Type":"BATTERY","Updated On":"11/08/2024 03:41:24 PM","Ward":"24","X Coordinate":"1158610","Y Coordinate":"1886654","Year":"2024"},{"Arrest":"false","Beat":"1222","Block":"030XX W WARREN BLVD","Case Number":"JH490982","Community Area":"27","Date":"10/31/2024 11:46:00 PM","Description":"AGGRAVATED - OTHER DANGEROUS WEAPON","District":"012","Domestic":"false","FBI Code":"04A","ID":"13649653","IUCR":"0530","Latitude":"41.881928563","Location":"(41.881928563, -87.702546038)","Location Description":"SIDEWALK","Longitude":"-87.702546038","Primary Type":"ASSAULT","Updated On":"11/08/2024 03:41:24 PM","Ward":"27","X Coordinate":"1156023","Y Coordinate":"1900196","Year":"2024"},{"Arrest":"false","Beat":"1925","Block":"006XX W GRACE ST","Case Number":"JH498953","Community Area":"6","Date":"11/01/2024 12:00:00 AM","Description":"FINANCIAL EXPLOITATION OF AN ELDERLY OR DISABLED PERSON","District":"019","Domestic":"false","FBI Code":"11","ID":"13656183","IUCR":"1195","Latitude":"","Location":"","Location Description":"APARTMENT","Longitude":"","Primary Type":"DECEPTIVE PRACTICE","Updated On":"11/08/2024 03:41:24 PM","Ward":"46","X Coordinate":"","Y Coordinate":"","Year":"2024"},{"Arrest":"true","Beat":"0815","Block":"048XX S KARLOV AVE","Case Number":"JH490945","Community Area":"57","Date":"10/31/2024 11:11:00 PM","Description":"TO VEHICLE","District":"008","Domestic":"false","FBI Code":"14","ID":"13649483","IUCR":"1320","Latitude":"41.805401949","Location":"(41.805401949, -87.725960745)","Location Description":"STREET","Longitude":"-87.725960745","Primary Type":"CRIMINAL DAMAGE","Updated On":"11/08/2024 03:41:24 PM","Ward":"14","X Coordinate":"1149844","Y Coordinate":"1872264","Year":"2024"},{"Arrest":"false","Beat":"0424","Block":"084XX S MACKINAW AVE","Case Number":"JH490979","Community Area":"46","Date":"10/31/2024 11:45:00 PM","Description":"AGGRAVATED VEHICULAR HIJACKING","District":"004","Domestic":"false","FBI Code":"03","ID":"13649571","IUCR":"0326","Latitude":"41.741990798","Location":"(41.741990798, -87.543000237)","Location Description":"STREET","Longitude":"-87.543000237","Primary Type":"ROBBERY","Updated On":"11/08/2024 03:41:24 PM","Ward":"10","X Coordinate":"1199939","Y Coordinate":"1849563","Year":"2024"},{"Arrest":"false","Beat":"1112","Block":"008XX N HAMLIN AVE","Case Number":"JH490939","Community Area":"23","Date":"10/31/2024 10:52:00 PM","Description":"DOMESTIC BATTERY SIMPLE","District":"011","Domestic":"true","FBI Code":"08B","ID":"13649467","IUCR":"0486","Latitude":"41.896409478","Location":"(41.896409478, -87.721224156)","Location Description":"STREET","Longitude":"-87.721224156","Primary Type":"BATTERY","Updated On":"11/08/2024 03:41:24 PM","Ward":"27","X Coordinate":"1150899","Y Coordinate":"1905436","Year":"2024"},{"Arrest":"false","Beat":"0131","Block":"021XX S MICHIGAN AVE","Case Number":"JH491558","Community Area":"33","Date":"11/01/2024 12:00:00 AM","Description":"OVER $500","District":"001","Domestic":"false","FBI Code":"06","ID":"13650061","IUCR":"0810","Latitude":"41.853683741","Location":"(41.853683741, -87.62383646)","Location Description":"STREET","Longitude":"-87.62383646","Primary Type":"THEFT","Updated On":"11/08/2024 03:41:24 PM","Ward":"3","X Coordinate":"1177542","Y Coordinate":"1890071","Year":"2024"},{"Arrest":"true","Beat":"1222","Block":"031XX W FULTON BLVD","Case Number":"JH490971","Community Area":"27","Date":"10/31/2024 11:45:00 PM","Description":"DOMESTIC BATTERY SIMPLE","District":"012","Domestic":"true","FBI Code":"08B","ID":"13649525","IUCR":"0486","Latitude":"41.886439909","Location":"(41.886439909, -87.705013622)","Location Description":"STREET","Longitude":"-87.705013622","Primary Type":"BATTERY","Updated On":"11/08/2024 03:41:24 PM","Ward":"27","X Coordinate":"1155339","Y Coordinate":"1901835","Year":"2024"},{"Arrest":"false","Beat":"0623","Block":"003XX W 76TH ST","Case Number":"JH490958","Community Area":"69","Date":"10/31/2024 11:08:00 PM","Description":"RECKLESS FIREARM DISCHARGE","District":"006","Domestic":"false","FBI Code":"15","ID":"13649469","IUCR":"1477","Latitude":"41.756270834","Location":"(41.756270834, -87.633350934)","Location Description":"STREET","Longitude":"-87.633350934","Primary Type":"WEAPONS VIOLATION","Updated On":"11/08/2024 03:41:24 PM","Ward":"17","X Coordinate":"1175239","Y Coordinate":"1854553","Year":"2024"},{"Arrest":"false","Beat":"0224","Block":"048XX S MICHIGAN AVE","Case Number":"JH491685","Community Area":"38","Date":"11/01/2024 12:00:00 AM","Description":"SIMPLE","District":"002","Domestic":"false","FBI Code":"08B","ID":"13650108","IUCR":"0460","Latitude":"41.807010932","Location":"(41.807010932, -87.622774469)","Location Description":"LIBRARY","Longitude":"-87.622774469","Primary Type":"BATTERY","Updated On":"11/08/2024 03:41:24 PM","Ward":"3","X Coordinate":"1177972","Y Coordinate":"1873066","Year":"2024"},{"Arrest":"false","Beat":"2024","Block":"049XX N SHERIDAN RD","Case Number":"JH490936","Community Area":"3","Date":"10/31/2024 10:50:00 PM","Description":"DOMESTIC BATTERY SIMPLE","District":"020","Domestic":"true","FBI Code":"08B","ID":"13649576","IUCR":"0486","Latitude":"41.972101049","Location":"(41.972101049, -87.654899332)","Location Description":"SIDEWALK","Longitude":"-87.654899332","Primary Type":"BATTERY","Updated On":"11/08/2024 03:41:24 PM","Ward":"48","X Coordinate":"1168738","Y Coordinate":"1933154","Year":"2024"},{"Arrest":"false","Beat":"1914","Block":"008XX W EASTWOOD AVE","Case Number":"JH493913","Community Area":"3","Date":"10/31/2024 11:45:00 PM","Description":"OVER $500","District":"019","Domestic":"false","FBI Code":"06","ID":"13651952","IUCR":"0810","Latitude":"41.966430564","Location":"(41.966430564, -87.651032417)","Location Description":"APARTMENT","Longitude":"-87.651032417","Primary Type":"THEFT","Updated On":"11/08/2024 03:41:24 PM","Ward":"46","X Coordinate":"1169806","Y Coordinate":"1931096","Year":"2024"},{"Arrest":"false","Beat":"1232","Block":"003XX S PEORIA ST","Case Number":"JH491869","Community Area":"28","Date":"11/01/2024 12:00:00 AM","Description":"FRAUD OR CONFIDENCE GAME","District":"012","Domestic":"false","FBI Code":"11","ID":"13650246","IUCR":"1130","Latitude":"41.877500741","Location":"(41.877500741, -87.649566735)","Location Description":"APARTMENT","Longitude":"-87.649566735","Primary Type":"DECEPTIVE PRACTICE","Updated On":"11/08/2024 03:41:24 PM","Ward":"34","X Coordinate":"1170463","Y Coordinate":"1898693","Year":"2024"},{"Arrest":"false","Beat":"0131","Block":"022XX S WABASH AVE","Case Number":"JH491083","Community Area":"33","Date":"10/31/2024 11:00:00 PM","Description":"THEFT FROM MOTOR VEHICLE","District":"001","Domestic":"false","FBI Code":"06","ID":"13649610","IUCR":"0710","Latitude":"41.85240964","Location":"(41.85240964, -87.625491255)","Location Description":"STREET","Longitude":"-87.625491255","Primary Type":"THEFT","Updated On":"11/08/2024 03:41:24 PM","Ward":"3","X Coordinate":"1177095","Y Coordinate":"1889603","Year":"2024"},{"Arrest":"false","Beat":"1925","Block":"036XX N HALSTED ST","Case Number":"JH491107","Community Area":"6","Date":"11/01/2024 12:00:00 AM","Description":"DOMESTIC BATTERY SIMPLE","District":"019","Domestic":"true","FBI Code":"08B","ID":"13649670","IUCR":"0486","Latitude":"41.948131367","Location":"(41.948131367, -87.649510899)","Location Description":"STREET","Longitude":"-87.649510899","Primary Type":"BATTERY","Updated On":"11/08/2024 03:41:24 PM","Ward":"46","X Coordinate":"1170273","Y Coordinate":"1924431","Year":"2024"},{"Arrest":"false","Beat":"2024","Block":"049XX N KENMORE AVE","Case Number":"JH491009","Community Area":"3","Date":"10/31/2024 11:45:00 PM","Description":"TO RESIDENCE","District":"020","Domestic":"false","FBI Code":"26","ID":"13653404","IUCR":"1365","Latitude":"41.972364558","Location":"(41.972364558, -87.656304974)","Location Description":"APARTMENT","Longitude":"-87.656304974","Primary Type":"CRIMINAL TRESPASS","Updated On":"11/08/2024 03:41:24 PM","Ward":"48","X Coordinate":"1168355","Y Coordinate":"1933247","Year":"2024"},{"Arrest":"false","Beat":"1922","Block":"033XX N PAULINA ST","Case Number":"JH491625","Community Area":"6","Date":"10/31/2024 11:00:00 PM","Description":"FROM BUILDING","District":"019","Domestic":"false","FBI Code":"06","ID":"13650015","IUCR":"0890","Latitude":"41.942687598","Location":"(41.942687598, -87.671174714)","Location Description":"APARTMENT","Longitude":"-87.671174714","Primary Type":"THEFT","Updated On":"11/08/2024 03:41:24 PM","Ward":"32","X Coordinate":"1164395","Y Coordinate":"1922401","Year":"2024"},{"Arrest":"false","Beat":"0726","Block":"064XX S SEELEY AVE","Case Number":"JH491166","Community Area":"67","Date":"10/31/2024 10:48:00 PM","Description":"VIOLATE ORDER OF PROTECTION","District":"007","Domestic":"true","FBI Code":"26","ID":"13649717","IUCR":"4387","Latitude":"41.776589139","Location":"(41.776589139, -87.675052781)","Location Description":"RESIDENCE","Longitude":"-87.675052781","Primary Type":"OTHER OFFENSE","Updated On":"11/08/2024 03:41:24 PM","Ward":"16","X Coordinate":"1163804","Y Coordinate":"1861867","Year":"2024"},{"Arrest":"false","Beat":"1132","Block":"039XX W ARTHINGTON ST","Case Number":"JH492309","Community Area":"26","Date":"11/01/2024 12:00:00 AM","Description":"DOMESTIC BATTERY SIMPLE","District":"011","Domestic":"true","FBI Code":"08B","ID":"13651617","IUCR":"0486","Latitude":"41.86983005","Location":"(41.86983005, -87.723541181)","Location Description":"RESIDENCE","Longitude":"-87.723541181","Primary Type":"BATTERY","Updated On":"11/08/2024 03:41:24 PM","Ward":"24","X Coordinate":"1150337","Y Coordinate":"1895746","Year":"2024"},{"Arrest":"false","Beat":"0633","Block":"093XX S EBERHART AVE","Case Number":"JH491190","Community Area":"49","Date":"10/31/2024 11:30:00 PM","Description":"AUTOMOBILE","District":"006","Domestic":"false","FBI Code":"07","ID":"13649715","IUCR":"0910","Latitude":"41.724978664","Location":"(41.724978664, -87.611802839)","Location Description":"STREET","Longitude":"-87.611802839","Primary Type":"MOTOR VEHICLE THEFT","Updated On":"11/08/2024 03:41:24 PM","Ward":"8","X Coordinate":"1181214","Y Coordinate":"1843199","Year":"2024"},{"Arrest":"false","Beat":"0233","Block":"052XX S WOODLAWN AVE","Case Number":"JH494780","Community Area":"41","Date":"10/31/2024 11:00:00 PM","Description":"SIMPLE","District":"002","Domestic":"false","FBI Code":"08B","ID":"13652808","IUCR":"0460","Latitude":"41.800452291","Location":"(41.800452291, -87.596664406)","Location Description":"APARTMENT","Longitude":"-87.596664406","Primary Type":"BATTERY","Updated On":"11/08/2024 03:41:24 PM","Ward":"5","X Coordinate":"1185111","Y Coordinate":"1870736","Year":"2024"},{"Arrest":"false","Beat":"0234","Block":"013XX E 53RD ST","Case Number":"JH491149","Community Area":"41","Date":"11/01/2024 12:00:00 AM","Description":"TO PROPERTY","District":"002","Domestic":"false","FBI Code":"14","ID":"13649966","IUCR":"1310","Latitude":"41.799483511","Location":"(41.799483511, -87.594093598)","Location Description":"COMMERCIAL / BUSINESS OFFICE","Longitude":"-87.594093598","Primary Type":"CRIMINAL DAMAGE","Updated On":"11/08/2024 03:41:24 PM","Ward":"4","X Coordinate":"1185815","Y Coordinate":"1870389","Year":"2024"},{"Arrest":"false","Beat":"1925","Block":"033XX N HALSTED ST","Case Number":"JH490927","Community Area":"6","Date":"10/31/2024 10:40:00 PM","Description":"AGGRAVATED - OTHER DANGEROUS WEAPON","District":"019","Domestic":"false","FBI Code":"04B","ID":"13649470","IUCR":"0430","Latitude":"41.942963116","Location":"(41.942963116, -87.649360288)","Location Description":"RESTAURANT","Longitude":"-87.649360288","Primary Type":"BATTERY","Updated On":"11/08/2024 03:41:24 PM","Ward":"44","X Coordinate":"1170329","Y Coordinate":"1922548","Year":"2024"},{"Arrest":"false","Beat":"1214","Block":"005XX N MILWAUKEE AVE","Case Number":"JH490944","Community Area":"24","Date":"10/31/2024 11:00:00 PM","Description":"SIMPLE","District":"012","Domestic":"false","FBI Code":"08B","ID":"13649498","IUCR":"0460","Latitude":"41.891412551","Location":"(41.891412551, -87.647934597)","Location Description":"CTA TRAIN","Longitude":"-87.647934597","Primary Type":"BATTERY","Updated On":"11/08/2024 03:41:24 PM","Ward":"27","X Coordinate":"1170867","Y Coordinate":"1903766","Year":"2024"},{"Arrest":"false","Beat":"1925","Block":"036XX N HALSTED ST","Case Number":"JH499752","Community Area":"6","Date":"10/31/2024 11:30:00 PM","Description":"AGGRAVATED - KNIFE / CUTTING INSTRUMENT","District":"019","Domestic":"false","FBI Code":"04B","ID":"13656805","IUCR":"0420","Latitude":"","Location":"","Location Description":"STREET","Longitude":"","Primary Type":"BATTERY","Updated On":"11/08/2024 03:41:24 PM","Ward":"46","X Coordinate":"","Y Coordinate":"","Year":"2024"},{"Arrest":"false","Beat":"0831","Block":"034XX W 65TH PL","Case Number":"JH490987","Community Area":"66","Date":"11/01/2024 12:00:00 AM","Description":"DOMESTIC BATTERY SIMPLE","District":"008","Domestic":"true","FBI Code":"08B","ID":"13649598","IUCR":"0486","Latitude":"41.77432858","Location":"(41.77432858, -87.708605612)","Location Description":"APARTMENT","Longitude":"-87.708605612","Primary Type":"BATTERY","Updated On":"11/08/2024 03:41:24 PM","Ward":"14","X Coordinate":"1154658","Y Coordinate":"1860975","Year":"2024"},{"Arrest":"false","Beat":"0334","Block":"023XX E 75TH ST","Case Number":"JH490961","Community Area":"43","Date":"10/31/2024 10:40:00 PM","Description":"OVER $500","District":"003","Domestic":"false","FBI Code":"06","ID":"13649518","IUCR":"0810","Latitude":"41.758979264","Location":"(41.758979264, -87.567088206)","Location Description":"GAS STATION","Longitude":"-87.567088206","Primary Type":"THEFT","Updated On":"11/08/2024 03:41:24 PM","Ward":"7","X Coordinate":"1193310","Y Coordinate":"1855694","Year":"2024"},{"Arrest":"false","Beat":"0432","Block":"104XX S INDIANAPOLIS AVE","Case Number":"JH490973","Community Area":"52","Date":"10/31/2024 11:00:00 PM","Description":"TO VEHICLE","District":"004","Domestic":"true","FBI Code":"14","ID":"13649577","IUCR":"1320","Latitude":"41.706137112","Location":"(41.706137112, -87.528084065)","Location Description":"RESIDENCE","Longitude":"-87.528084065","Primary Type":"CRIMINAL DAMAGE","Updated On":"11/08/2024 03:41:24 PM","Ward":"10","X Coordinate":"1204132","Y Coordinate":"1836536","Year":"2024"},{"Arrest":"false","Beat":"2432","Block":"064XX N GLENWOOD AVE","Case Number":"JH490931","Community Area":"1","Date":"10/31/2024 10:40:00 PM","Description":"STRONG ARM - NO WEAPON","District":"024","Domestic":"true","FBI Code":"03","ID":"13649560","IUCR":"0320","Latitude":"41.998666791","Location":"(41.998666791, -87.665525159)","Location Description":"APARTMENT","Longitude":"-87.665525159","Primary Type":"ROBBERY","Updated On":"11/08/2024 03:41:24 PM","Ward":"49","X Coordinate":"1165773","Y Coordinate":"1942812","Year":"2024"},{"Arrest":"true","Beat":"2011","Block":"030XX W PETERSON AVE","Case Number":"JH490968","Community Area":"2","Date":"10/31/2024 11:30:00 PM","Description":"AGGRAVATED - KNIFE / CUTTING INSTRUMENT","District":"020","Domestic":"false","FBI Code":"04A","ID":"13649558","IUCR":"0520","Latitude":"41.990409975","Location":"(41.990409975, -87.704977986)","Location Description":"SMALL RETAIL STORE","Longitude":"-87.704977986","Primary Type":"ASSAULT","Updated On":"11/08/2024 03:41:24 PM","Ward":"50","X Coordinate":"1155071","Y Coordinate":"1939722","Year":"2024"},{"Arrest":"false","Beat":"0433","Block":"127XX S CARONDOLET AVE","Case Number":"JH490942","Community Area":"51","Date":"10/31/2024 11:00:00 PM","Description":"AGG. DOMESTIC BATTERY - HANDS, FISTS, FEET, SERIOUS INJURY","District":"004","Domestic":"true","FBI Code":"04B","ID":"13649580","IUCR":"0498","Latitude":"41.664168299","Location":"(41.664168299, -87.549548487)","Location Description":"RESIDENCE","Longitude":"-87.549548487","Primary Type":"BATTERY","Updated On":"11/08/2024 03:41:24 PM","Ward":"10","X Coordinate":"1198410","Y Coordinate":"1821189","Year":"2024"},{"Arrest":"false","Beat":"1114","Block":"002XX N KOSTNER AVE","Case Number":"JH490991","Community Area":"26","Date":"10/31/2024 11:30:00 PM","Description":"OVER $500","District":"011","Domestic":"false","FBI Code":"06","ID":"13649565","IUCR":"0810","Latitude":"41.883820405","Location":"(41.883820405, -87.735578199)","Location Description":"APARTMENT","Longitude":"-87.735578199","Primary Type":"THEFT","Updated On":"11/08/2024 03:41:24 PM","Ward":"28","X Coordinate":"1147023","Y Coordinate":"1900821","Year":"2024"},{"Arrest":"true","Beat":"1221","Block":"022XX W HURON ST","Case Number":"JH492075","Community Area":"24","Date":"10/31/2024 10:36:00 PM","Description":"LIQUOR LICENSE VIOLATION","District":"012","Domestic":"false","FBI Code":"22","ID":"13650473","IUCR":"2250","Latitude":"41.894003939","Location":"(41.894003939, -87.682509158)","Location Description":"COMMERCIAL / BUSINESS OFFICE","Longitude":"-87.682509158","Primary Type":"LIQUOR LAW VIOLATION","Updated On":"11/08/2024 03:41:24 PM","Ward":"36","X Coordinate":"1161446","Y Coordinate":"1904637","Year":"2024"},{"Arrest":"false","Beat":"1833","Block":"003XX E CHICAGO AVE","Case Number":"JH491353","Community Area":"8","Date":"10/31/2024 11:00:00 PM","Description":"TO VEHICLE","District":"018","Domestic":"false","FBI Code":"14","ID":"13649780","IUCR":"1320","Latitude":"41.896811851","Location":"(41.896811851, -87.618896542)","Location Description":"STREET","Longitude":"-87.618896542","Primary Type":"CRIMINAL DAMAGE","Updated On":"11/08/2024 03:41:24 PM","Ward":"2","X Coordinate":"1178757","Y Coordinate":"1905798","Year":"2024"},{"Arrest":"false","Beat":"1612","Block":"059XX N NEWARK AVE","Case Number":"JH497075","Community Area":"10","Date":"11/01/2024 12:00:00 AM","Description":"CHILD ABUSE","District":"016","Domestic":"true","FBI Code":"08B","ID":"13654501","IUCR":"1750","Latitude":"41.989463109","Location":"(41.989463109, -87.79690992)","Location Description":"RESIDENCE","Longitude":"-87.79690992","Primary Type":"OFFENSE INVOLVING CHILDREN","Updated On":"11/08/2024 03:41:24 PM","Ward":"41","X Coordinate":"1130081","Y Coordinate":"1939207","Year":"2024"},{"Arrest":"false","Beat":"1413","Block":"034XX W MEDILL AVE","Case Number":"JH492174","Community Area":"22","Date":"10/31/2024 11:30:00 PM","Description":"TO VEHICLE","District":"014","Domestic":"false","FBI Code":"14","ID":"13650475","IUCR":"1320","Latitude":"41.923745067","Location":"(41.923745067, -87.712584865)","Location Description":"STREET","Longitude":"-87.712584865","Primary Type":"CRIMINAL DAMAGE","Updated On":"11/08/2024 03:41:24 PM","Ward":"35","X Coordinate":"1153179","Y Coordinate":"1915414","Year":"2024"},{"Arrest":"false","Beat":"0725","Block":"067XX S ASHLAND AVE","Case Number":"JH490943","Community Area":"67","Date":"10/31/2024 11:00:00 PM","Description":"AGGRAVATED - HANDGUN","District":"007","Domestic":"false","FBI Code":"04B","ID":"13649581","IUCR":"041A","Latitude":"41.7715691","Location":"(41.7715691, -87.664003785)","Location Description":"SIDEWALK","Longitude":"-87.664003785","Primary Type":"BATTERY","Updated On":"11/08/2024 03:41:24 PM","Ward":"16","X Coordinate":"1166832","Y Coordinate":"1860061","Year":"2024"},{"Arrest":"false","Beat":"1831","Block":"004XX N FRANKLIN ST","Case Number":"JH491325","Community Area":"8","Date":"10/31/2024 11:00:00 PM","Description":"THEFT FROM MOTOR VEHICLE","District":"018","Domestic":"false","FBI Code":"06","ID":"13649863","IUCR":"0710","Latitude":"41.890207286","Location":"(41.890207286, -87.635541212)","Location Description":"PARKING LOT / GARAGE (NON RESIDENTIAL)","Longitude":"-87.635541212","Primary Type":"THEFT","Updated On":"11/08/2024 03:41:24 PM","Ward":"42","X Coordinate":"1174245","Y Coordinate":"1903354","Year":"2024"},{"Arrest":"false","Beat":"0131","Block":"0000X W CERMAK RD","Case Number":"JH490922","Community Area":"33","Date":"10/31/2024 10:35:00 PM","Description":"SIMPLE","District":"001","Domestic":"false","FBI Code":"08B","ID":"13650084","IUCR":"0460","Latitude":"41.852903905","Location":"(41.852903905, -87.62821668)","Location Description":"SIDEWALK","Longitude":"-87.62821668","Primary Type":"BATTERY","Updated On":"11/08/2024 03:41:24 PM","Ward":"3","X Coordinate":"1176351","Y Coordinate":"1889777","Year":"2024"},{"Arrest":"false","Beat":"1923","Block":"008XX W GRACE ST","Case Number":"JH491602","Community Area":"6","Date":"11/01/2024 12:00:00 AM","Description":"AGGRAVATED - OTHER DANGEROUS WEAPON","District":"019","Domestic":"false","FBI Code":"04B","ID":"13650046","IUCR":"0430","Latitude":"41.951186446","Location":"(41.951186446, -87.650562715)","Location Description":"STREET","Longitude":"-87.650562715","Primary Type":"BATTERY","Updated On":"11/08/2024 03:41:24 PM","Ward":"46","X Coordinate":"1169978","Y Coordinate":"1925542","Year":"2024"},{"Arrest":"false","Beat":"2412","Block":"067XX N CALIFORNIA AVE","Case Number":"JH492483","Community Area":"2","Date":"10/31/2024 10:34:00 PM","Description":"HARASSMENT BY TELEPHONE","District":"024","Domestic":"false","FBI Code":"26","ID":"13650754","IUCR":"2825","Latitude":"42.003814365","Location":"(42.003814365, -87.699805605)","Location Description":"APARTMENT","Longitude":"-87.699805605","Primary Type":"OTHER OFFENSE","Updated On":"11/08/2024 03:41:24 PM","Ward":"50","X Coordinate":"1156441","Y Coordinate":"1944617","Year":"2024"},{"Arrest":"false","Beat":"0421","Block":"076XX S PHILLIPS AVE","Case Number":"JH490994","Community Area":"43","Date":"10/31/2024 11:00:00 PM","Description":"DOMESTIC BATTERY SIMPLE","District":"004","Domestic":"true","FBI Code":"08B","ID":"13649678","IUCR":"0486","Latitude":"41.756548345","Location":"(41.756548345, -87.565112352)","Location Description":"RESIDENCE","Longitude":"-87.565112352","Primary Type":"BATTERY","Updated On":"11/08/2024 03:41:24 PM","Ward":"7","X Coordinate":"1193857","Y Coordinate":"1854813","Year":"2024"},{"Arrest":"false","Beat":"1831","Block":"002XX W ONTARIO ST","Case Number":"JH491843","Community Area":"8","Date":"10/31/2024 11:30:00 PM","Description":"SIMPLE","District":"018","Domestic":"false","FBI Code":"08B","ID":"13650519","IUCR":"0460","Latitude":"41.89318177","Location":"(41.89318177, -87.6345943)","Location Description":"BAR OR TAVERN","Longitude":"-87.6345943","Primary Type":"BATTERY","Updated On":"11/08/2024 03:41:24 PM","Ward":"42","X Coordinate":"1174494","Y Coordinate":"1904440","Year":"2024"},{"Arrest":"false","Beat":"0822","Block":"032XX W 55TH ST","Case Number":"JH492982","Community Area":"63","Date":"11/01/2024 12:00:00 AM","Description":"STRONG ARM - NO WEAPON","District":"008","Domestic":"false","FBI Code":"03","ID":"13651154","IUCR":"0320","Latitude":"41.793489634","Location":"(41.793489634, -87.70515582)","Location Description":"STREET","Longitude":"-87.70515582","Primary Type":"ROBBERY","Updated On":"11/08/2024 03:41:24 PM","Ward":"14","X Coordinate":"1155548","Y Coordinate":"1867964","Year":"2024"},{"Arrest":"false","Beat":"1624","Block":"060XX W IRVING PARK RD","Case Number":"JH491692","Community Area":"15","Date":"10/31/2024 11:30:00 PM","Description":"AGGRAVATED - HANDS, FISTS, FEET, SERIOUS INJURY","District":"016","Domestic":"false","FBI Code":"04B","ID":"13650103","IUCR":"0479","Latitude":"41.953044506","Location":"(41.953044506, -87.777256854)","Location Description":"SIDEWALK","Longitude":"-87.777256854","Primary Type":"BATTERY","Updated On":"11/08/2024 03:41:24 PM","Ward":"38","X Coordinate":"1135510","Y Coordinate":"1925970","Year":"2024"},{"Arrest":"false","Beat":"0726","Block":"063XX S DAMEN AVE","Case Number":"JH490930","Community Area":"67","Date":"10/31/2024 10:56:00 PM","Description":"AGGRAVATED - OTHER DANGEROUS WEAPON","District":"007","Domestic":"false","FBI Code":"04B","ID":"13649548","IUCR":"0430","Latitude":"41.778868505","Location":"(41.778868505, -87.673896581)","Location Description":"GAS STATION","Longitude":"-87.673896581","Primary Type":"BATTERY","Updated On":"11/08/2024 03:41:24 PM","Ward":"16","X Coordinate":"1164113","Y Coordinate":"1862700","Year":"2024"},{"Arrest":"false","Beat":"1111","Block":"006XX N CICERO AVE","Case Number":"JH492806","Community Area":"25","Date":"11/01/2024 12:00:00 AM","Description":"UNLAWFUL ENTRY","District":"011","Domestic":"false","FBI Code":"05","ID":"13656067","IUCR":"0620","Latitude":"","Location":"","Location Description":"CONVENIENCE STORE","Longitude":"","Primary Type":"BURGLARY","Updated On":"11/08/2024 03:41:24 PM","Ward":"28","X Coordinate":"","Y Coordinate":"","Year":"2024"},{"Arrest":"false","Beat":"2532","Block":"016XX N LATROBE AVE","Case Number":"JH492755","Community Area":"25","Date":"10/31/2024 11:27:00 PM","Description":"TO VEHICLE","District":"025","Domestic":"false","FBI Code":"14","ID":"13650986","IUCR":"1320","Latitude":"41.910189107","Location":"(41.910189107, -87.7569086)","Location Description":"STREET","Longitude":"-87.7569086","Primary Type":"CRIMINAL DAMAGE","Updated On":"11/08/2024 03:41:24 PM","Ward":"37","X Coordinate":"1141150","Y Coordinate":"1910390","Year":"2024"},{"Arrest":"false","Beat":"1014","Block":"015XX S RIDGEWAY AVE","Case Number":"JH490925","Community Area":"29","Date":"10/31/2024 10:31:00 PM","Description":"RECKLESS FIREARM DISCHARGE","District":"010","Domestic":"false","FBI Code":"15","ID":"13649455","IUCR":"1477","Latitude":"41.860098871","Location":"(41.860098871, -87.718898118)","Location Description":"STREET","Longitude":"-87.718898118","Primary Type":"WEAPONS VIOLATION","Updated On":"11/08/2024 03:41:24 PM","Ward":"24","X Coordinate":"1151627","Y Coordinate":"1892209","Year":"2024"},{"Arrest":"false","Beat":"0234","Block":"013XX E 53RD ST","Case Number":"JH491043","Community Area":"41","Date":"10/31/2024 10:30:00 PM","Description":"SIMPLE","District":"002","Domestic":"false","FBI Code":"08B","ID":"13649573","IUCR":"0460","Latitude":"41.799483511","Location":"(41.799483511, -87.594093598)","Location Description":"SIDEWALK","Longitude":"-87.594093598","Primary Type":"BATTERY","Updated On":"11/08/2024 03:41:24 PM","Ward":"4","X Coordinate":"1185815","Y Coordinate":"1870389","Year":"2024"},{"Arrest":"false","Beat":"2222","Block":"089XX S LAFLIN ST","Case Number":"JH491940","Community Area":"73","Date":"11/01/2024 12:00:00 AM","Description":"SIMPLE","District":"022","Domestic":"true","FBI Code":"08A","ID":"13650227","IUCR":"0560","Latitude":"41.731462584","Location":"(41.731462584, -87.660503907)","Location Description":"RESIDENCE","Longitude":"-87.660503907","Primary Type":"ASSAULT","Updated On":"11/08/2024 03:41:24 PM","Ward":"21","X Coordinate":"1167901","Y Coordinate":"1845454","Year":"2024"},{"Arrest":"false","Beat":"1831","Block":"003XX W OHIO ST","Case Number":"JH491289","Community Area":"8","Date":"11/01/2024 12:00:00 AM","Description":"OVER $500","District":"018","Domestic":"false","FBI Code":"06","ID":"13649850","IUCR":"0810","Latitude":"41.892358446","Location":"(41.892358446, -87.636391922)","Location Description":"STREET","Longitude":"-87.636391922","Primary Type":"THEFT","Updated On":"11/08/2024 03:41:24 PM","Ward":"42","X Coordinate":"1174007","Y Coordinate":"1904136","Year":"2024"},{"Arrest":"false","Beat":"0835","Block":"025XX W COLUMBUS AVE","Case Number":"JH492223","Community Area":"66","Date":"10/31/2024 10:30:00 PM","Description":"AUTOMOBILE","District":"008","Domestic":"false","FBI Code":"07","ID":"13650526","IUCR":"0910","Latitude":"41.757361447","Location":"(41.757361447, -87.686937269)","Location Description":"STREET","Longitude":"-87.686937269","Primary Type":"MOTOR VEHICLE THEFT","Updated On":"11/08/2024 03:41:24 PM","Ward":"18","X Coordinate":"1160615","Y Coordinate":"1854836","Year":"2024"},{"Arrest":"false","Beat":"1215","Block":"015XX W CARROLL AVE","Case Number":"JH491764","Community Area":"28","Date":"11/01/2024 12:00:00 AM","Description":"$500 AND UNDER","District":"012","Domestic":"false","FBI Code":"06","ID":"13650185","IUCR":"0820","Latitude":"41.88741592","Location":"(41.88741592, -87.664988379)","Location Description":"STREET","Longitude":"-87.664988379","Primary Type":"THEFT","Updated On":"11/08/2024 03:41:24 PM","Ward":"27","X Coordinate":"1166235","Y Coordinate":"1902273","Year":"2024"},{"Arrest":"false","Beat":"0725","Block":"014XX W MARQUETTE RD","Case Number":"JH491011","Community Area":"67","Date":"10/31/2024 10:30:00 PM","Description":"AUTOMOBILE","District":"007","Domestic":"false","FBI Code":"07","ID":"13649545","IUCR":"0910","Latitude":"41.772250908","Location":"(41.772250908, -87.659986167)","Location Description":"APARTMENT","Longitude":"-87.659986167","Primary Type":"MOTOR VEHICLE THEFT","Updated On":"11/08/2024 03:41:24 PM","Ward":"16","X Coordinate":"1167926","Y Coordinate":"1860318","Year":"2024"},{"Arrest":"false","Beat":"1614","Block":"055XX N CUMBERLAND AVE","Case Number":"JH491702","Community Area":"10","Date":"10/31/2024 10:30:00 PM","Description":"AUTOMOBILE","District":"016","Domestic":"false","FBI Code":"07","ID":"13650213","IUCR":"0910","Latitude":"41.980349758","Location":"(41.980349758, -87.836582213)","Location Description":"PARKING LOT / GARAGE (NON RESIDENTIAL)","Longitude":"-87.836582213","Primary Type":"MOTOR VEHICLE THEFT","Updated On":"11/08/2024 03:41:24 PM","Ward":"41","X Coordinate":"1119315","Y Coordinate":"1935821","Year":"2024"},{"Arrest":"true","Beat":"0231","Block":"003XX E 53RD ST","Case Number":"JH490932","Community Area":"40","Date":"10/31/2024 10:22:00 PM","Description":"FALSE / STOLEN / ALTERED TRP","District":"002","Domestic":"false","FBI Code":"26","ID":"13649471","IUCR":"502P","Latitude":"41.798448373","Location":"(41.798448373, -87.61696452)","Location Description":"STREET","Longitude":"-87.61696452","Primary Type":"OTHER OFFENSE","Updated On":"11/08/2024 03:41:24 PM","Ward":"3","X Coordinate":"1179582","Y Coordinate":"1869959","Year":"2024"},{"Arrest":"false","Beat":"0321","Block":"066XX S KENWOOD AVE","Case Number":"JH490941","Community Area":"42","Date":"10/31/2024 10:20:00 PM","Description":"AGG. DOMESTIC BATTERY - HANDS, FISTS, FEET, SERIOUS INJURY","District":"003","Domestic":"true","FBI Code":"04B","ID":"13649554","IUCR":"0498","Latitude":"41.774478372","Location":"(41.774478372, -87.592936381)","Location Description":"APARTMENT","Longitude":"-87.592936381","Primary Type":"BATTERY","Updated On":"11/08/2024 03:41:24 PM","Ward":"20","X Coordinate":"1186209","Y Coordinate":"1861280","Year":"2024"}]